{
  "INTRO_BANNER_1_TITLE": "Бестеневой осветитель",
  "VIDEO1_PATH": "/video/intro.mp4",
  "INTRO_BANNER_2_TITLE_2_1": "ТОЛКОВЫЙ",
  "INTRO_BANNER_2_TITLE_2_2": "ВЫБОР",
  "INTRO_BANNER_2_TEXT": "Для любой процедуры, где необходим качественный свет.\n<br/>Работайте, не отвлекаясь на тени!\n",
  "TO_VIDEO": "Видео",
  "BRIGHT": "Бестеневой осветитель",
  "NEW_VERSION_ENABLE": "Новый налобный осветитель BiLumix 2 поколения. <a class='black' href='/package/headlamp'>В продаже!</a>",
  "STAY_UPDATED_H1": "Оставайтесь в курсе",
  "STAY_UPDATED_TEXT": "Наших эксклюзивных предложений и акций на нашу продукцию",
  "AGREE_WITH": "Согласен с ",
  "AGREE_WITH_PRIVACY": "условиями использования данных",
  "ENTER_YOUR_EMAIL": "Укажите ваш email",
  "SUBSCRIBE": "Подписаться",
  "SPECIAL_OFFERS_H1": "Специальные предложения",
  "SPECIAL_OFFERS_TEXT": "Вскоре здесь будут размещены наши акции и предложения"
}